gspread_leo/__init__.py
gspread_leo/gspread_leo.py
gspread_leo-0.1.5.dist-info/METADATA
gspread_leo-0.1.5.dist-info/WHEEL
gspread_leo-0.1.5.dist-info/RECORD
