Metadata-Version: 2.1
Name: gspread-leo
Version: 0.1.5
Summary: 
Author: leomoraesguitar
Author-email: 123950901+leomoraesguitar@users.noreply.github.com
Requires-Python: >=3.11,<4.0
Classifier: Programming Language :: Python :: 3
Classifier: Programming Language :: Python :: 3.11
Classifier: Programming Language :: Python :: 3.12
Requires-Dist: gspread (>=5.12.4,<6.0.0)
